{
  "kind": "collectionType",
  "collectionName": "g_characters",
  "info": {
    "singularName": "g-character",
    "pluralName": "g-characters",
    "displayName": "g_character",
    "description": ""
  },
  "options": {
    "draftAndPublish": false
  },
  "pluginOptions": {},
  "attributes": {
    "name": {
      "type": "string",
      "required": true,
      "maxLength": 15,
      "minLength": 5,
      "unique": true
    },
    "max_hp": {
      "type": "string",
      "default": "200"
    },
    "current_hp": {
      "type": "string",
      "default": "200"
    },
    "exp": {
      "type": "string",
      "default": "0"
    },
    "gold": {
      "type": "string",
      "default": "1000"
    },
    "point": {
      "type": "integer",
      "default": 0
    },
    "account_id": {
      "type": "integer",
      "required": true
    },
    "location": {
      "type": "integer",
      "required": true,
      "default": 1
    },
    "atk": {
      "type": "integer",
      "required": true,
      "default": 10
    },
    "def": {
      "type": "integer",
      "default": 10,
      "required": true
    },
    "dex": {
      "type": "integer",
      "default": 10,
      "required": true
    },
    "lvl": {
      "type": "string",
      "default": "1",
      "required": true
    }
  }
}
